py_fbchat/__init__.py
py_fbchat/_attachment.py
py_fbchat/_client.py
py_fbchat/_core.py
py_fbchat/_exception.py
py_fbchat/_file.py
py_fbchat/_graphql.py
py_fbchat/_group.py
py_fbchat/_location.py
py_fbchat/_message.py
py_fbchat/_mqtt.py
py_fbchat/_page.py
py_fbchat/_quick_reply.py
py_fbchat/_state.py
py_fbchat/_sticker.py
py_fbchat/_thread.py
py_fbchat/_user.py
py_fbchat/_util.py
py_fbchat/models.py
py_fbchat-1.9.94.dist-info/WHEEL
py_fbchat-1.9.94.dist-info/METADATA
py_fbchat-1.9.94.dist-info/RECORD
