Metadata-Version: 2.1
Name: py_fbchat
Version: 1.9.94
Summary: Facebook Chat (Messenger) for Python
Home-page: https://github.com/carpedm20/fbchat/
License: BSD 3-Clause
Keywords: Facebook FB Messenger Library Chat Api Bot
Author: Taehoon Kim
Author-email: carpedm20@gmail.com
Maintainer: Mads Marquart
Maintainer-email: madsmtm@gmail.com
Requires-Python: >=2.7, !=3.0.*, !=3.1.*, !=3.2.*, !=3.3.*, <4.0
Classifier: Development Status :: 3 - Alpha
Classifier: Intended Audience :: Developers
Classifier: Intended Audience :: Information Technology
Classifier: License :: OSI Approved :: BSD License
Classifier: Operating System :: OS Independent
Classifier: Natural Language :: English
Classifier: Programming Language :: Python
Classifier: Programming Language :: Python :: 2.7
Classifier: Programming Language :: Python :: 3
Classifier: Programming Language :: Python :: 3.4
Classifier: Programming Language :: Python :: 3.5
Classifier: Programming Language :: Python :: 3.6
Classifier: Programming Language :: Python :: 3.7
Classifier: Programming Language :: Python :: Implementation :: CPython
Classifier: Programming Language :: Python :: Implementation :: PyPy
Classifier: Topic :: Communications :: Chat
Classifier: Topic :: Internet :: WWW/HTTP
Classifier: Topic :: Internet :: WWW/HTTP :: Dynamic Content
Classifier: Topic :: Software Development :: Libraries
Classifier: Topic :: Software Development :: Libraries :: Python Modules
Requires-Dist: aenum~=2.0
Requires-Dist: attrs>=18.2
Requires-Dist: requests~=2.19
Requires-Dist: beautifulsoup4~=4.0
Requires-Dist: paho-mqtt~=1.5
Requires-Dist: sphinx~=2.0 ; extra == "docs"
Requires-Dist: sphinxcontrib-spelling~=4.0 ; extra == "docs"
Requires-Dist: black ; extra == "lint"
Requires-Dist: pytest~=4.0 ; extra == "test"
Requires-Dist: six~=1.0 ; extra == "test"
Requires-Dist: bump2version~=0.5.0 ; extra == "tools"
Project-URL: Documentation, https://fbchat.readthedocs.io/
Project-URL: Repository, https://github.com/carpedm20/fbchat/
Provides-Extra: docs
Provides-Extra: lint
Provides-Extra: test
Provides-Extra: tools
